{
  "project_info": {
    "project_number": "828379572147",
    "firebase_url": "https://dequarantine-aae5f.firebaseio.com",
    "project_id": "dequarantine-aae5f",
    "storage_bucket": "dequarantine-aae5f.appspot.com"
  },
  "client": [
    {
      "client_info": {
        "mobilesdk_app_id": "1:828379572147:android:a5fdfb8a68d9fc2b284dc6",
        "android_client_info": {
          "package_name": "com.dq.dequarantine"
        }
      },
      "oauth_client": [
        {
          "client_id": "828379572147-fq36c6ct551l1llcv3v79j0er417gcgi.apps.googleusercontent.com",
          "client_type": 1,
          "android_info": {
            "package_name": "com.dq.dequarantine",
            "certificate_hash": "f20d6b95724f1eaad05565a819802ff67e2e5419"
          }
        },
        {
          "client_id": "828379572147-sfte7etqbq4b7v7vus25loifrq07mllr.apps.googleusercontent.com",
          "client_type": 3
        }
      ],
      "api_key": [
        {
          "current_key": "AIzaSyD-IAofPumamfTSTVBMsyh-yW6aDwe5GME"
        }
      ],
      "services": {
        "appinvite_service": {
          "other_platform_oauth_client": [
            {
              "client_id": "828379572147-sfte7etqbq4b7v7vus25loifrq07mllr.apps.googleusercontent.com",
              "client_type": 3
            }
          ]
        }
      }
    }
  ],
  "configuration_version": "1"
}